Workbook

Sheet How to Use
A1: Monthly Numbers Dashboard
A3: 1. Transactions: add one row per sale or expense, with a date, the type (Sale or Expense), a category from the Dashboard list and the amount.
A4: 2. Dashboard: type the first day of the month you want in the yellow cell. Everything else updates: revenue, gross margin, cash in and out, the change from last month, and your top 5 expenses.
A5: 3. Observations: each month, write three sentences about what the numbers say, or ask Claude for Excel to draft them and check every figure it cites.
A6: Cost of goods = the categories Materials and Jars & packaging. Change the list in the Dashboard if your direct costs are different.
A7: Owner's pay, transfers between your own accounts and cash floats are not expenses: leave them out of Transactions.
A9: Legend
A10: Yellow cell, blue text: fill in your own value. The values shown are a fictional example.
A11: Black text: formula. Don't type over it.
A12: Green text: formula that pulls a value from another sheet.
A14: From the book 30 Claude Workflows for Small Business Owners (Monarch Lane Press). All businesses and figures in the examples are fictional.

Sheet Dashboard
B2: Monthly Numbers Dashboard
B4: Month (first day) | C4: 46266
B5: Previous month | C5: =EDATE(C4,-1) -> 46235
B6: Next month starts | C6: =EDATE(C4,1) -> 46296
B8: Key numbers | C8: This month | D8: Last month | E8: Change
B9: Revenue (cash in from sales) | C9: =SUMIFS(Transactions!$E$2:$E$500,Transactions!$B$2:$B$500,"Sale",Transactions!$A$2:$A$500,">="&$C$4,Transactions!$A$2:$A$500,"<"&$C$6) -> 6499.33 | D9: =SUMIFS(Transactions!$E$2:$E$500,Transactions!$B$2:$B$500,"Sale",Transactions!$A$2:$A$500,">="&$C$5,Transactions!$A$2:$A$500,"<"&$C$4) -> 6921.52 | E9: =IF(D9=0,"",(C9-D9)/ABS(D9)) -> -0.060996717
B10: Cost of goods | C10: =SUMIFS(Transactions!$E$2:$E$500,Transactions!$B$2:$B$500,"Expense",Transactions!$A$2:$A$500,">="&$C$4,Transactions!$A$2:$A$500,"<"&$C$6,Transactions!$C$2:$C$500,"Materials")+SUMIFS(Transactions!$E$2:$E$500,Transactions!$B$2:$B$500,"Expense",Transactions!$A$2:$A$500,">="&$C$4,Transactions!$A$2:$A$500,"<"&$C$6,Transactions!$C$2:$C$500,"Jars & packaging") -> 1689.46 | D10: =SUMIFS(Transactions!$E$2:$E$500,Transactions!$B$2:$B$500,"Expense",Transactions!$A$2:$A$500,">="&$C$5,Transactions!$A$2:$A$500,"<"&$C$4,Transactions!$C$2:$C$500,"Materials")+SUMIFS(Transactions!$E$2:$E$500,Transactions!$B$2:$B$500,"Expense",Transactions!$A$2:$A$500,">="&$C$5,Transactions!$A$2:$A$500,"<"&$C$4,Transactions!$C$2:$C$500,"Jars & packaging") -> 2005.08 | E10: =IF(D10=0,"",(C10-D10)/ABS(D10)) -> -0.15741018
B11: Gross profit | C11: =C9-C10 -> 4809.87 | D11: =D9-D10 -> 4916.44 | E11: =IF(D11=0,"",(C11-D11)/ABS(D11)) -> -0.021676254
B12: Gross margin | C12: =IF(C9=0,0,C11/C9) -> 0.74005628 | D12: =IF(D9=0,0,D11/D9) -> 0.71031219 | E12: =C12-D12 -> 0.029744097
B13: Total expenses (cash out) | C13: =SUMIFS(Transactions!$E$2:$E$500,Transactions!$B$2:$B$500,"Expense",Transactions!$A$2:$A$500,">="&$C$4,Transactions!$A$2:$A$500,"<"&$C$6) -> 3305.33 | D13: =SUMIFS(Transactions!$E$2:$E$500,Transactions!$B$2:$B$500,"Expense",Transactions!$A$2:$A$500,">="&$C$5,Transactions!$A$2:$A$500,"<"&$C$4) -> 3444.33 | E13: =IF(D13=0,"",(C13-D13)/ABS(D13)) -> -0.04035618
B14: Net cash for the month | C14: =C9-C13 -> 3194 | D14: =D9-D13 -> 3477.19 | E14: =IF(D14=0,"",(C14-D14)/ABS(D14)) -> -0.081442199
B15: Gross margin change is shown in percentage points.
B17: Expenses by category | C17: This month | D17: Last month
B18: Materials | C18: =SUMIFS(Transactions!$E$2:$E$500,Transactions!$B$2:$B$500,"Expense",Transactions!$A$2:$A$500,">="&$C$4,Transactions!$A$2:$A$500,"<"&$C$6,Transactions!$C$2:$C$500,$B18) -> 796.31 | D18: =SUMIFS(Transactions!$E$2:$E$500,Transactions!$B$2:$B$500,"Expense",Transactions!$A$2:$A$500,">="&$C$5,Transactions!$A$2:$A$500,"<"&$C$4,Transactions!$C$2:$C$500,$B18) -> 1137.87
B19: Jars & packaging | C19: =SUMIFS(Transactions!$E$2:$E$500,Transactions!$B$2:$B$500,"Expense",Transactions!$A$2:$A$500,">="&$C$4,Transactions!$A$2:$A$500,"<"&$C$6,Transactions!$C$2:$C$500,$B19) -> 893.15 | D19: =SUMIFS(Transactions!$E$2:$E$500,Transactions!$B$2:$B$500,"Expense",Transactions!$A$2:$A$500,">="&$C$5,Transactions!$A$2:$A$500,"<"&$C$4,Transactions!$C$2:$C$500,$B19) -> 867.21
B20: Postage | C20: =SUMIFS(Transactions!$E$2:$E$500,Transactions!$B$2:$B$500,"Expense",Transactions!$A$2:$A$500,">="&$C$4,Transactions!$A$2:$A$500,"<"&$C$6,Transactions!$C$2:$C$500,$B20) -> 841.85 | D20: =SUMIFS(Transactions!$E$2:$E$500,Transactions!$B$2:$B$500,"Expense",Transactions!$A$2:$A$500,">="&$C$5,Transactions!$A$2:$A$500,"<"&$C$4,Transactions!$C$2:$C$500,$B20) -> 836.23
B21: Marketplace & payment fees | C21: =SUMIFS(Transactions!$E$2:$E$500,Transactions!$B$2:$B$500,"Expense",Transactions!$A$2:$A$500,">="&$C$4,Transactions!$A$2:$A$500,"<"&$C$6,Transactions!$C$2:$C$500,$B21) -> 171.01 | D21: =SUMIFS(Transactions!$E$2:$E$500,Transactions!$B$2:$B$500,"Expense",Transactions!$A$2:$A$500,">="&$C$5,Transactions!$A$2:$A$500,"<"&$C$4,Transactions!$C$2:$C$500,$B21) -> 175.56
B22: Software | C22: =SUMIFS(Transactions!$E$2:$E$500,Transactions!$B$2:$B$500,"Expense",Transactions!$A$2:$A$500,">="&$C$4,Transactions!$A$2:$A$500,"<"&$C$6,Transactions!$C$2:$C$500,$B22) -> 92.98 | D22: =SUMIFS(Transactions!$E$2:$E$500,Transactions!$B$2:$B$500,"Expense",Transactions!$A$2:$A$500,">="&$C$5,Transactions!$A$2:$A$500,"<"&$C$4,Transactions!$C$2:$C$500,$B22) -> 92.98
B23: Market booth fees | C23: =SUMIFS(Transactions!$E$2:$E$500,Transactions!$B$2:$B$500,"Expense",Transactions!$A$2:$A$500,">="&$C$4,Transactions!$A$2:$A$500,"<"&$C$6,Transactions!$C$2:$C$500,$B23) -> 60 | D23: =SUMIFS(Transactions!$E$2:$E$500,Transactions!$B$2:$B$500,"Expense",Transactions!$A$2:$A$500,">="&$C$5,Transactions!$A$2:$A$500,"<"&$C$4,Transactions!$C$2:$C$500,$B23) -> 60
B24: Marketing | C24: =SUMIFS(Transactions!$E$2:$E$500,Transactions!$B$2:$B$500,"Expense",Transactions!$A$2:$A$500,">="&$C$4,Transactions!$A$2:$A$500,"<"&$C$6,Transactions!$C$2:$C$500,$B24) -> 375.03 | D24: =SUMIFS(Transactions!$E$2:$E$500,Transactions!$B$2:$B$500,"Expense",Transactions!$A$2:$A$500,">="&$C$5,Transactions!$A$2:$A$500,"<"&$C$4,Transactions!$C$2:$C$500,$B24) -> 274.48
B25: Other | C25: =SUMIFS(Transactions!$E$2:$E$500,Transactions!$B$2:$B$500,"Expense",Transactions!$A$2:$A$500,">="&$C$4,Transactions!$A$2:$A$500,"<"&$C$6,Transactions!$C$2:$C$500,$B25) -> 75 | D25: =SUMIFS(Transactions!$E$2:$E$500,Transactions!$B$2:$B$500,"Expense",Transactions!$A$2:$A$500,">="&$C$5,Transactions!$A$2:$A$500,"<"&$C$4,Transactions!$C$2:$C$500,$B25) -> 0
B28: Top 5 expenses this month | C28: Amount | D28: Rank
B29: =INDEX($B$18:$B$25,MATCH(C29,$C$18:$C$25,0)) -> Jars & packaging | C29: =LARGE($C$18:$C$25,D29) -> 893.15 | D29: 1
B30: =INDEX($B$18:$B$25,MATCH(C30,$C$18:$C$25,0)) -> Postage | C30: =LARGE($C$18:$C$25,D30) -> 841.85 | D30: 2
B31: =INDEX($B$18:$B$25,MATCH(C31,$C$18:$C$25,0)) -> Materials | C31: =LARGE($C$18:$C$25,D31) -> 796.31 | D31: 3
B32: =INDEX($B$18:$B$25,MATCH(C32,$C$18:$C$25,0)) -> Marketing | C32: =LARGE($C$18:$C$25,D32) -> 375.03 | D32: 4
B33: =INDEX($B$18:$B$25,MATCH(C33,$C$18:$C$25,0)) -> Marketplace & payment fees | C33: =LARGE($C$18:$C$25,D33) -> 171.01 | D33: 5
B34: If two categories have exactly the same amount, the first one is listed twice.
B36: Observations (write three each month)
B37: Revenue fell about 6% to $6,499 (C9). All of the drop came from the website; Etsy held steady and the market grew.
B38: Gross margin rose from 71.0% to 74.0% (C12), mostly because August included a large wax order.
B39: Postage, at $842, now costs more than materials, at $796 (C20, C18). Check that the shipping customers pay still covers it.

Sheet Transactions
A1: Date | B1: Type | C1: Category | D1: Description | E1: Amount
A2: 46204 | B2: Expense | C2: Marketplace & payment fees | D2: Etsy fees | E2: 154.95
A3: 46206 | B3: Expense | C3: Software | D3: Design app | E3: 14.99
A4: 46206 | B4: Expense | C4: Software | D4: Website plan | E4: 39
A5: 46207 | B5: Sale | C5: Sales: website | D5: Website payout | E5: 967.43
A6: 46208 | B6: Sale | C6: Sales: Etsy | D6: Etsy deposit | E6: 565.74
A7: 46209 | B7: Expense | C7: Materials | D7: Wax and fragrance oil | E7: 410.36
A8: 46210 | B8: Expense | C8: Postage | D8: Postage labels | E8: 422.45
A9: 46212 | B9: Expense | C9: Jars & packaging | D9: Jars | E9: 622.68
A10: 46213 | B10: Expense | C10: Software | D10: Newsletter tool | E10: 29
A11: 46214 | B11: Sale | C11: Sales: website | D11: Website payout | E11: 920.73
A12: 46215 | B12: Sale | C12: Sales: Etsy | D12: Etsy deposit | E12: 538.51
A13: 46216 | B13: Expense | C13: Market booth fees | D13: Booth fee | E13: 60
... A68: 46291 | B68: Sale | C68: Sales: Etsy | D68: Etsy deposit | E68: 573.69
