Workbook

Sheet How to Use
A1: Price It Right: Custom Order Calculator
A3: 1. Calculator: list what one order uses, your labor time, your hourly rate and your overhead per labor hour. The sheet gives your true cost, a suggested price for your target margin, and your margin at today's price.
A4: 2. Scenarios: test what happens if an ingredient gets more expensive, a job takes longer, or you change your price.
A5: Overhead per labor hour = your monthly rent, utilities, insurance and equipment costs, divided by the hours you actually spend producing in a month.
A6: Tip: in Claude for Excel, ask Claude to explain any number in this sheet; it answers with links to the cells it used.
A8: Legend
A9: Yellow cell, blue text: fill in your own value. The values shown are a fictional example.
A10: Black text: formula. Don't type over it.
A11: Green text: formula that pulls a value from another sheet.
A13: From the book 30 Claude Workflows for Small Business Owners (Monarch Lane Press). All businesses and figures in the examples are fictional.

Sheet Calculator
A1: Price It Right: Custom Order Calculator
A2: Example: Maple & Rye Bakery, one 8-inch two-layer custom cake. Replace the yellow cells with your own numbers.
A4: Material | B4: Quantity used | C4: Unit | D4: Cost per unit | E4: Cost
A5: Flour | B5: 1.5 | C5: lb | D5: 0.6 | E5: =IF(OR(B5="",D5=""),0,B5*D5) -> 0.9
A6: Sugar | B6: 1.2 | C6: lb | D6: 0.8 | E6: =IF(OR(B6="",D6=""),0,B6*D6) -> 0.96
A7: Butter | B7: 1 | C7: lb | D7: 4.5 | E7: =IF(OR(B7="",D7=""),0,B7*D7) -> 4.5
A8: Eggs | B8: 8 | C8: each | D8: 0.35 | E8: =IF(OR(B8="",D8=""),0,B8*D8) -> 2.8
A9: Heavy cream | B9: 1 | C9: pint | D9: 3.2 | E9: =IF(OR(B9="",D9=""),0,B9*D9) -> 3.2
A10: Fondant and decorations | B10: 1 | C10: lot | D10: 6 | E10: =IF(OR(B10="",D10=""),0,B10*D10) -> 6
A11: Cake box and board | B11: 1 | C11: each | D11: 3.5 | E11: =IF(OR(B11="",D11=""),0,B11*D11) -> 3.5
E12: =IF(OR(B12="",D12=""),0,B12*D12) -> 0
E13: =IF(OR(B13="",D13=""),0,B13*D13) -> 0
E14: =IF(OR(B14="",D14=""),0,B14*D14) -> 0
D15: Materials total | E15: =SUM(E5:E14) -> 21.86
A17: Labor minutes per order | B17: 150
A18: Hourly labor rate | B18: 22
A19: Labor cost | B19: =B17/60*B18 -> 55
A21: Overhead per labor hour | B21: 9
A22: Overhead cost | B22: =B17/60*B21 -> 22.5
A24: Total cost per order | B24: =E15+B19+B22 -> 99.36
A25: Target margin | B25: 0.35
A26: Suggested price | B26: =IF(B25>=1,0,B24/(1-B25)) -> 152.86154
A27: Suggested price, rounded up to $5 | B27: =CEILING(B26,5) -> 155
A28: Break-even price (zero profit) | B28: =B24 -> 99.36
A30: Your current price | B30: 110
A31: Profit per order at current price | B31: =B30-B24 -> 10.64
A32: Margin at current price | B32: =IF(B30=0,0,(B30-B24)/B30) -> 0.096727273

Sheet Scenarios
A1: Scenarios
A2: Change the yellow cells to test a cost increase, a longer job or a new price. Rates come from the Calculator sheet.
B4: Today | C4: Butter up 20% | D4: New price
A5: Butter cost change | B5: 0 | C5: 0.2 | D5: 0
A6: Labor minutes | B6: 150 | C6: 150 | D6: 150
A7: Price | B7: 110 | C7: 110 | D7: 135
A8: Materials | B8: =Calculator!$E$15+Calculator!$E$7*B5 -> 21.86 | C8: =Calculator!$E$15+Calculator!$E$7*C5 -> 22.76 | D8: =Calculator!$E$15+Calculator!$E$7*D5 -> 21.86
A9: Labor | B9: =B6/60*Calculator!$B$18 -> 55 | C9: =C6/60*Calculator!$B$18 -> 55 | D9: =D6/60*Calculator!$B$18 -> 55
A10: Overhead | B10: =B6/60*Calculator!$B$21 -> 22.5 | C10: =C6/60*Calculator!$B$21 -> 22.5 | D10: =D6/60*Calculator!$B$21 -> 22.5
A11: Total cost | B11: =SUM(B8:B10) -> 99.36 | C11: =SUM(C8:C10) -> 100.26 | D11: =SUM(D8:D10) -> 99.36
A12: Profit per order | B12: =B7-B11 -> 10.64 | C12: =C7-C11 -> 9.74 | D12: =D7-D11 -> 35.64
A13: Margin | B13: =IF(B7=0,0,B12/B7) -> 0.096727273 | C13: =IF(C7=0,0,C12/C7) -> 0.088545455 | D13: =IF(D7=0,0,D12/D7) -> 0.264
